robotchain_sdk/__init__.py
robotchain_sdk/board/__init__.py
robotchain_sdk/ros/__init__.py
robotchain_sdk/utils/__init__.py
robotchain_sdk/utils/list/__init__.py
robotchain_sdk/utils/loging/__init__.py
robotchain_sdk/utils/random/__init__.py
robotchain_sdk-1.0.6.dist-info/METADATA
robotchain_sdk-1.0.6.dist-info/WHEEL
robotchain_sdk-1.0.6.dist-info/top_level.txt
robotchain_sdk-1.0.6.dist-info/RECORD
